{"entities":{"Q240468":{"pageid":233785,"ns":0,"title":"Q240468","lastrevid":892201116,"modified":"2019-03-24T07:44:59Z","type":"item","id":"Q240468","labels":{"zh-hans":{"language":"zh-hans","value":"\u53d9\u5229\u4e9a\u9551"},"zh-hant":{"language":"zh-hant","value":"\u6558\u5229\u4e9e\u938a"},"zh-hk":{"language":"zh-hk","value":"\u6558\u5229\u4e9e\u938a"},"zh-cn":{"language":"zh-cn","value":"\u53d9\u5229\u4e9a\u9551"},"zh-sg":{"language":"zh-sg","value":"\u53d9\u5229\u4e9a\u9551"},"zh-tw":{"language":"zh-tw","value":"\u6558\u5229\u4e9e\u938a"},"pl":{"language":"pl","value":"Funt syryjski"},"fr":{"language":"fr","value":"livre syrienne"},"he":{"language":"he","value":"\u05dc\u05d9\u05e8\u05d4 \u05e1\u05d5\u05e8\u05d9\u05ea"},"arz":{"language":"arz","value":"\u0644\u064a\u0631\u0627 \u0633\u0648\u0631\u064a\u0629"},"ko":{"language":"ko","value":"\uc2dc\ub9ac\uc544 \ud30c\uc6b4\ub4dc"},"es":{"language":"es","value":"libra siria"},"yo":{"language":"yo","value":"Ponun S\u00edr\u00ed\u00e0"},"hu":{"language":"hu","value":"sz\u00edr font"},"it":{"language":"it","value":"lira siriana"},"de":{"language":"de","value":"syrische Lira"},"ja":{"language":"ja","value":"\u30b7\u30ea\u30a2\u30fb\u30dd\u30f3\u30c9"},"el":{"language":"el","value":"\u039b\u03af\u03c1\u03b1 \u03a3\u03c5\u03c1\u03af\u03b1\u03c2"},"sv":{"language":"sv","value":"Syriskt pund"},"ar":{"language":"ar","value":"\u0644\u064a\u0631\u0629 \u0633\u0648\u0631\u064a\u0629"},"nl":{"language":"nl","value":"Syrisch pond"},"pt":{"language":"pt","value":"libra s\u00edria"},"eo":{"language":"eo","value":"siria pundo"},"tg-latn":{"language":"tg-latn","value":"Funti Sirija"},"ru":{"language":"ru","value":"\u0441\u0438\u0440\u0438\u0439\u0441\u043a\u0438\u0439 \u0444\u0443\u043d\u0442"},"sr-el":{"language":"sr-el","value":"sirijska funta"},"sr-ec":{"language":"sr-ec","value":"\u0441\u0438\u0440\u0438\u0458\u0441\u043a\u0430 \u0444\u0443\u043d\u0442\u0430"},"en":{"language":"en","value":"Syrian pound"},"tr":{"language":"tr","value":"Suriye liras\u0131"},"ca":{"language":"ca","value":"lliura siriana"},"be-tarask":{"language":"be-tarask","value":"\u0421\u044b\u0440\u044b\u0439\u0441\u043a\u0456 \u0444\u0443\u043d\u0442"},"sl":{"language":"sl","value":"Sirski funt"},"fa":{"language":"fa","value":"\u0644\u06cc\u0631\u0647 \u0633\u0648\u0631\u06cc\u0647"},"mr":{"language":"mr","value":"\u0938\u093f\u0930\u093f\u092f\u0928 \u092a\u093e\u0909\u0902\u0921"},"kv":{"language":"kv","value":"\u0421\u0438\u0440\u0438\u044f\u0441\u0430 \u0444\u0443\u043d\u0442"},"bpy":{"language":"bpy","value":"\u09b8\u09bf\u09b0\u09bf\u09af\u09bc\u09be\u09a8 \u09aa\u09be\u0989\u09a8\u09cd\u09a1"},"lt":{"language":"lt","value":"Sirijos svaras"},"be":{"language":"be","value":"\u0421\u0456\u0440\u044b\u0439\u0441\u043a\u0456 \u0444\u0443\u043d\u0442"},"sr":{"language":"sr","value":"\u0441\u0438\u0440\u0438\u0458\u0441\u043a\u0430 \u0444\u0443\u043d\u0442\u0430"},"uk":{"language":"uk","value":"\u0421\u0438\u0440\u0456\u0439\u0441\u044c\u043a\u0438\u0439 \u0444\u0443\u043d\u0442"},"tg":{"language":"tg","value":"\u0424\u0443\u043d\u0442\u0438 \u0421\u0438\u0440\u0438\u044f"},"zh":{"language":"zh","value":"\u6558\u5229\u4e9e\u938a"},"pa":{"language":"pa","value":"\u0a38\u0a40\u0a30\u0a40\u0a06\u0a08 \u0a2a\u0a3e\u0a0a\u0a02\u0a21"},"nb":{"language":"nb","value":"syrisk pund"},"fi":{"language":"fi","value":"Syyrian punta"},"sah":{"language":"sah","value":"\u0421\u0438\u0440\u0438\u044f \u043b\u0438\u0440\u0430\u0442\u0430"},"hr":{"language":"hr","value":"Sirijska funta"},"jbo":{"language":"jbo","value":"lo ru'ursujepu"},"is":{"language":"is","value":"S\u00fdrlenskt pund"},"mt":{"language":"mt","value":"lira Sirjana"},"xmf":{"language":"xmf","value":"\u10e1\u10d8\u10e0\u10d8\u10e3\u10da\u10d8 \u10d2\u10d8\u10e0\u10d5\u10d0\u10dc\u10e5\u10d0"},"ka":{"language":"ka","value":"\u10e1\u10d8\u10e0\u10d8\u10e3\u10da\u10d8 \u10e4\u10e3\u10dc\u10e2\u10d8"},"cs":{"language":"cs","value":"Syrsk\u00e1 libra"},"hi":{"language":"hi","value":"\u0938\u0940\u0930\u093f\u092f\u0928 \u092a\u093e\u0909\u0902\u0921"},"tt":{"language":"tt","value":"\u0421\u04af\u0440\u0438\u044f \u0444\u0443\u043d\u0442\u044b"},"id":{"language":"id","value":"Pound Suriah"},"bg":{"language":"bg","value":"\u0421\u0438\u0440\u0438\u0439\u0441\u043a\u0430 \u043b\u0438\u0440\u0430"},"az":{"language":"az","value":"Suriya funtu"},"nan":{"language":"nan","value":"Su-l\u012b-a pound"}},"descriptions":{"pa":{"language":"pa","value":"\u0a38\u0a40\u0a30\u0a40\u0a06 \u0a26\u0a40 \u0a2e\u0a41\u0a26\u0a30\u0a3e"},"ja":{"language":"ja","value":"\u30b7\u30ea\u30a2\u306e\u901a\u8ca8"},"en":{"language":"en","value":"currency"},"es":{"language":"es","value":"moneda de Siria"},"ru":{"language":"ru","value":"\u0432\u0430\u043b\u044e\u0442\u0430 \u0421\u0438\u0440\u0438\u0438"},"nl":{"language":"nl","value":"valuta"},"ar":{"language":"ar","value":"\u0627\u0644\u0639\u0645\u0644\u0629 \u0627\u0644\u0631\u0633\u0645\u064a\u0629 \u0644\u0644\u062c\u0645\u0647\u0648\u0631\u064a\u0629 \u0627\u0644\u0639\u0631\u0628\u064a\u0629 \u0627\u0644\u0633\u0648\u0631\u064a\u0629"},"id":{"language":"id","value":"Mata Uang Suriah"},"fa":{"language":"fa","value":"\u06cc\u06a9\u0627\u06cc \u067e\u0648\u0644 \u0633\u0648\u0631\u06cc\u0647"}},"aliases":{"ko":[{"language":"ko","value":"\uc2dc\ub9ac\uc544 \ub9ac\ub77c"}],"es":[{"language":"es","value":"libra de Siria"},{"language":"es","value":"SYP"}],"yo":[{"language":"yo","value":"Syrian pound"}],"de":[{"language":"de","value":"SYP"},{"language":"de","value":"Syrisches Pfund"}],"sv":[{"language":"sv","value":"SYP"},{"language":"sv","value":"Syrisk lira"}],"ar":[{"language":"ar","value":"\u0627\u0644\u0644\u064a\u0631\u0629 \u0627\u0644\u0633\u0648\u0631\u064a\u0629"},{"language":"ar","value":"\u0644\u064a\u0631\u0647 \u0633\u0648\u0631\u064a\u0647"},{"language":"ar","value":"\u0644\u064a\u0631\u0627\u062a \u0633\u0648\u0631\u064a\u0629"}],"nl":[{"language":"nl","value":"Syrische lira"}],"pt":[{"language":"pt","value":"Libra da S\u00edria"}],"ru":[{"language":"ru","value":"\u0412\u0430\u043b\u044e\u0442\u0430 \u0421\u0438\u0440\u0438\u0438"},{"language":"ru","value":"\u0421\u0438\u0440\u0438\u0439\u0441\u043a\u0438\u0439 \u0444\u0443\u043d\u0442"}],"ca":[{"language":"ca","value":"Lira s\u00edria"},{"language":"ca","value":"Lira de S\u00edria"},{"language":"ca","value":"Lliura de S\u00edria"}],"sl":[{"language":"sl","value":"Sirska lira"},{"language":"sl","value":"SYP"},{"language":"sl","value":"Sirijska lira"},{"language":"sl","value":"Sirijski funt"}],"fa":[{"language":"fa","value":"\u067e\u0648\u0646\u062f \u0633\u0648\u0631\u06cc\u0647"},{"language":"fa","value":"\u0644\u06cc\u0631\u0647\u0654 \u0633\u0648\u0631\u06cc\u0647"}],"nb":[{"language":"nb","value":"Syriske pund"},{"language":"nb","value":"SYP"}],"eo":[{"language":"eo","value":"SYP"}],"cs":[{"language":"cs","value":"SYP"}],"en":[{"language":"en","value":"SYP"}]},"claims":{"P373":[{"mainsnak":{"snaktype":"value","property":"P373","hash":"7573de851548f8fdf6c76fc8ccacc4bb395e3bee","datavalue":{"value":"Money of Syria","type":"string"},"datatype":"string"},"type":"statement","id":"q240468$53EF2508-85A9-4AB2-879D-B9DA5D0794E4","rank":"normal"}],"P31":[{"mainsnak":{"snaktype":"value","property":"P31","hash":"724bdf3e32380d29eaccfd480beedeb2e3ddd017","datavalue":{"value":{"entity-type":"item","numeric-id":8142,"id":"Q8142"},"type":"wikibase-entityid"},"datatype":"wikibase-item"},"type":"statement","id":"q240468$B507F25D-7104-4BB3-90A9-982B5AB9898D","rank":"normal"}],"P498":[{"mainsnak":{"snaktype":"value","property":"P498","hash":"4e74694c257d7fd1aa0d0d3cd27d4ad24c82278c","datavalue":{"value":"SYP","type":"string"},"datatype":"external-id"},"type":"statement","id":"q240468$df15edb4-415f-0ebd-26ec-baddced8797d","rank":"normal"}],"P562":[{"mainsnak":{"snaktype":"value","property":"P562","hash":"27d2f888e522e4f0f33dff3d23781f2245e91889","datavalue":{"value":{"entity-type":"item","numeric-id":806932,"id":"Q806932"},"type":"wikibase-entityid"},"datatype":"wikibase-item"},"type":"statement","id":"q240468$1E4626C0-D015-4161-A2DB-47BCD6521F1F","rank":"normal","references":[{"hash":"fa278ebfc458360e5aed63d5058cca83c46134f1","snaks":{"P143":[{"snaktype":"value","property":"P143","hash":"e4f6d9441d0600513c4533c672b5ab472dc73694","datavalue":{"value":{"entity-type":"item","numeric-id":328,"id":"Q328"},"type":"wikibase-entityid"},"datatype":"wikibase-item"}]},"snaks-order":["P143"]}]}],"P646":[{"mainsnak":{"snaktype":"value","property":"P646","hash":"0c09f5a2c1c64d898aaae68fc8ff14c400ec7c08","datavalue":{"value":"/m/02br6q","type":"string"},"datatype":"external-id"},"type":"statement","id":"Q240468$3F89B630-7E96-4648-BEBA-14A65F41CACF","rank":"normal","references":[{"hash":"2b00cb481cddcac7623114367489b5c194901c4a","snaks":{"P248":[{"snaktype":"value","property":"P248","hash":"a94b740202b097dd33355e0e6c00e54b9395e5e0","datavalue":{"value":{"entity-type":"item","numeric-id":15241312,"id":"Q15241312"},"type":"wikibase-entityid"},"datatype":"wikibase-item"}],"P577":[{"snaktype":"value","property":"P577","hash":"fde79ecb015112d2f29229ccc1ec514ed3e71fa2","datavalue":{"value":{"time":"+2013-10-28T00:00:00Z","timezone":0,"before":0,"after":0,"precision":11,"calendarmodel":"http://www.wikidata.org/entity/Q1985727"},"type":"time"},"datatype":"time"}]},"snaks-order":["P248","P577"]}]}],"P17":[{"mainsnak":{"snaktype":"value","property":"P17","hash":"ae7fde79651f636944bfc709e15c77e77f1d523b","datavalue":{"value":{"entity-type":"item","numeric-id":858,"id":"Q858"},"type":"wikibase-entityid"},"datatype":"wikibase-item"},"type":"statement","id":"Q240468$27a350d1-4a13-6106-9a3b-e86812681235","rank":"normal"}],"P279":[{"mainsnak":{"snaktype":"value","property":"P279","hash":"a5deda76ddd740ba283d06c5a3f23fb7a79c89bd","datavalue":{"value":{"entity-type":"item","numeric-id":339180,"id":"Q339180"},"type":"wikibase-entityid"},"datatype":"wikibase-item"},"type":"statement","id":"Q240468$a58fb735-4322-62d2-f461-c2d48d95519a","rank":"normal"}],"P3347":[{"mainsnak":{"snaktype":"value","property":"P3347","hash":"a52df8c4b60e17e233aa2a86b91bce0408ca6c0e","datavalue":{"value":"500256","type":"string"},"datatype":"external-id"},"type":"statement","id":"Q240468$1004C304-174B-4E1C-9575-1BB2D268CCE0","rank":"normal"}],"P18":[{"mainsnak":{"snaktype":"value","property":"P18","hash":"65153866c4b5716d1aa0eff8bfa9e012a066670b","datavalue":{"value":"NewSyrian1000front.png","type":"string"},"datatype":"commonsMedia"},"type":"statement","id":"Q240468$0DE8ABA7-ECC7-41EE-A899-4653F1D886FF","rank":"normal","references":[{"hash":"8605252f0b1d16a133349818b8f17d921ea86c70","snaks":{"P143":[{"snaktype":"value","property":"P143","hash":"5a343e7e758a4282a01316d3e959b6e653b767fc","datavalue":{"value":{"entity-type":"item","numeric-id":11920,"id":"Q11920"},"type":"wikibase-entityid"},"datatype":"wikibase-item"}],"P4656":[{"snaktype":"value","property":"P4656","hash":"389bbc3e0fe12c274ebc34be9409d842e5584ac0","datavalue":{"value":"https://it.wikipedia.org/w/index.php?title=Lira_siriana&oldid=98980161","type":"string"},"datatype":"url"}]},"snaks-order":["P143","P4656"]}]}]},"sitelinks":{"arwiki":{"site":"arwiki","title":"\u0644\u064a\u0631\u0629 \u0633\u0648\u0631\u064a\u0629","badges":[]},"arzwiki":{"site":"arzwiki","title":"\u0644\u064a\u0631\u0627 \u0633\u0648\u0631\u064a\u0629","badges":[]},"azwiki":{"site":"azwiki","title":"Suriya funtu","badges":[]},"be_x_oldwiki":{"site":"be_x_oldwiki","title":"\u0421\u044b\u0440\u044b\u0439\u0441\u043a\u0456 \u0444\u0443\u043d\u0442","badges":[]},"bewiki":{"site":"bewiki","title":"\u0421\u0456\u0440\u044b\u0439\u0441\u043a\u0456 \u0444\u0443\u043d\u0442","badges":[]},"bgwiki":{"site":"bgwiki","title":"\u0421\u0438\u0440\u0438\u0439\u0441\u043a\u0430 \u043b\u0438\u0440\u0430","badges":[]},"bpywiki":{"site":"bpywiki","title":"\u09b8\u09bf\u09b0\u09bf\u09af\u09bc\u09be\u09a8 \u09aa\u09be\u0989\u09a8\u09cd\u09a1","badges":[]},"cawiki":{"site":"cawiki","title":"Lliura siriana","badges":[]},"commonswiki":{"site":"commonswiki","title":"Category:Money of Syria","badges":[]},"cswiki":{"site":"cswiki","title":"Syrsk\u00e1 libra","badges":[]},"dewiki":{"site":"dewiki","title":"Syrische Lira","badges":[]},"elwiki":{"site":"elwiki","title":"\u039b\u03af\u03c1\u03b1 \u03a3\u03c5\u03c1\u03af\u03b1\u03c2","badges":[]},"enwiki":{"site":"enwiki","title":"Syrian pound","badges":[]},"eowiki":{"site":"eowiki","title":"Siria pundo","badges":[]},"eswiki":{"site":"eswiki","title":"Libra siria","badges":[]},"fawiki":{"site":"fawiki","title":"\u0644\u06cc\u0631\u0647 \u0633\u0648\u0631\u06cc\u0647","badges":[]},"fiwiki":{"site":"fiwiki","title":"Syyrian punta","badges":[]},"frwiki":{"site":"frwiki","title":"Livre syrienne","badges":[]},"hewiki":{"site":"hewiki","title":"\u05dc\u05d9\u05e8\u05d4 \u05e1\u05d5\u05e8\u05d9\u05ea","badges":[]},"hiwiki":{"site":"hiwiki","title":"\u0938\u0940\u0930\u093f\u092f\u0928 \u092a\u093e\u0909\u0902\u0921","badges":[]},"hrwiki":{"site":"hrwiki","title":"Sirijska funta","badges":[]},"huwiki":{"site":"huwiki","title":"Sz\u00edr font","badges":[]},"idwiki":{"site":"idwiki","title":"Pound Suriah","badges":[]},"iswiki":{"site":"iswiki","title":"S\u00fdrlenskt pund","badges":[]},"itwiki":{"site":"itwiki","title":"Lira siriana","badges":[]},"jawiki":{"site":"jawiki","title":"\u30b7\u30ea\u30a2\u30fb\u30dd\u30f3\u30c9","badges":[]},"kawiki":{"site":"kawiki","title":"\u10e1\u10d8\u10e0\u10d8\u10e3\u10da\u10d8 \u10d2\u10d8\u10e0\u10d5\u10d0\u10dc\u10e5\u10d0","badges":[]},"kowiki":{"site":"kowiki","title":"\uc2dc\ub9ac\uc544 \ud30c\uc6b4\ub4dc","badges":[]},"kvwiki":{"site":"kvwiki","title":"\u0421\u0438\u0440\u0438\u044f\u0441\u0430 \u0444\u0443\u043d\u0442","badges":[]},"ltwiki":{"site":"ltwiki","title":"Sirijos svaras","badges":[]},"mrwiki":{"site":"mrwiki","title":"\u0938\u093f\u0930\u093f\u092f\u0928 \u092a\u093e\u0909\u0902\u0921","badges":[]},"nlwiki":{"site":"nlwiki","title":"Syrisch pond","badges":[]},"nowiki":{"site":"nowiki","title":"Syrisk pund","badges":[]},"pawiki":{"site":"pawiki","title":"\u0a38\u0a40\u0a30\u0a40\u0a06\u0a08 \u0a2a\u0a3e\u0a0a\u0a02\u0a21","badges":[]},"plwiki":{"site":"plwiki","title":"Funt syryjski","badges":[]},"ptwiki":{"site":"ptwiki","title":"Libra s\u00edria","badges":[]},"ruwiki":{"site":"ruwiki","title":"\u0421\u0438\u0440\u0438\u0439\u0441\u043a\u0438\u0439 \u0444\u0443\u043d\u0442","badges":[]},"sahwiki":{"site":"sahwiki","title":"\u0421\u0438\u0440\u0438\u044f \u043b\u0438\u0440\u0430\u0442\u0430","badges":[]},"slwiki":{"site":"slwiki","title":"Sirski funt","badges":[]},"srwiki":{"site":"srwiki","title":"\u0421\u0438\u0440\u0438\u0458\u0441\u043a\u0430 \u0444\u0443\u043d\u0442\u0430","badges":[]},"svwiki":{"site":"svwiki","title":"Syriskt pund","badges":[]},"tgwiki":{"site":"tgwiki","title":"\u0424\u0443\u043d\u0442\u0438 \u0421\u0438\u0440\u0438\u044f","badges":[]},"trwiki":{"site":"trwiki","title":"Suriye liras\u0131","badges":[]},"ukwiki":{"site":"ukwiki","title":"\u0421\u0438\u0440\u0456\u0439\u0441\u044c\u043a\u0438\u0439 \u0444\u0443\u043d\u0442","badges":[]},"xmfwiki":{"site":"xmfwiki","title":"\u10e1\u10d8\u10e0\u10d8\u10e3\u10da\u10d8 \u10d2\u10d8\u10e0\u10d5\u10d0\u10dc\u10e5\u10d0","badges":[]},"yowiki":{"site":"yowiki","title":"Ponun S\u00edr\u00ed\u00e0","badges":[]},"zh_min_nanwiki":{"site":"zh_min_nanwiki","title":"Su-l\u012b-a pound","badges":[]},"zhwiki":{"site":"zhwiki","title":"\u6558\u5229\u4e9e\u938a","badges":[]}}}},"success":1}